odoo/addons/pos_partner_location_abstract/README.rst
odoo/addons/pos_partner_location_abstract/__init__.py
odoo/addons/pos_partner_location_abstract/__manifest__.py
odoo/addons/pos_partner_location_abstract/i18n/it.po
odoo/addons/pos_partner_location_abstract/i18n/pos_partner_location_abstract.pot
odoo/addons/pos_partner_location_abstract/models/__init__.py
odoo/addons/pos_partner_location_abstract/models/address_struct.py
odoo/addons/pos_partner_location_abstract/models/pos_config.py
odoo/addons/pos_partner_location_abstract/models/pos_session.py
odoo/addons/pos_partner_location_abstract/models/res_partner.py
odoo/addons/pos_partner_location_abstract/readme/CONTRIBUTORS.rst
odoo/addons/pos_partner_location_abstract/readme/DESCRIPTION.rst
odoo/addons/pos_partner_location_abstract/readme/ROADMAP.rst
odoo/addons/pos_partner_location_abstract/static/description/icon.png
odoo/addons/pos_partner_location_abstract/static/description/index.html
odoo/addons/pos_partner_location_abstract/static/src/css/map_popup.css
odoo/addons/pos_partner_location_abstract/static/src/js/PartnerDetailsMapEdit.esm.js
odoo/addons/pos_partner_location_abstract/static/src/js/PartnerMapEdit.esm.js
odoo/addons/pos_partner_location_abstract/static/src/tests/tours/PartnerDetailTour.tour.esm.js
odoo/addons/pos_partner_location_abstract/static/src/xml/PartnerDetailsEdit.xml
odoo/addons/pos_partner_location_abstract/static/src/xml/PartnerMapEdit.xml
odoo/addons/pos_partner_location_abstract/tests/__init__.py
odoo/addons/pos_partner_location_abstract/tests/test_address_struct.py
odoo/addons/pos_partner_location_abstract/tests/test_pos_config.py
odoo/addons/pos_partner_location_abstract/tests/test_pos_session.py
odoo/addons/pos_partner_location_abstract/tests/test_pos_ui.py
odoo_addon_pos_partner_location_abstract-16.0.1.0.1.dist-info/METADATA
odoo_addon_pos_partner_location_abstract-16.0.1.0.1.dist-info/WHEEL
odoo_addon_pos_partner_location_abstract-16.0.1.0.1.dist-info/top_level.txt
odoo_addon_pos_partner_location_abstract-16.0.1.0.1.dist-info/RECORD
